{
    "seg_length" : 44100,
    "sample_rate" : 44100,
    "bit_depth" : 16,
    "n_mfcc" : 13,
    "log_mel": true,
    "num_quantiles" : 2,
    "boolean_encoding" : "onehot-dense",
    "n_fft": 800,
    "win_length": 280,
    "hop_length" : 100,
    "n_mels" : 80,
    "center" : false,
    "class_type" : "vowel",
    "out_path_x": "path",
    "out_path_y": "path",
    "avg_mfccs": false,
    "delay_bools": true,
    "train_directory" : "PATH",
    "test_directory" : "PATH",
    "data_out_path" : "PATH",
    "fold" : 0
}